pydsxkline/__init__.py
pydsxkline/dsxkline.py
pydsxkline/dsxkline_html.py
pydsxkline/dsxkline_js.py
pydsxkline/qqhq.py
pydsxkline-1.2.1.dist-info/LICENSE
pydsxkline-1.2.1.dist-info/METADATA
pydsxkline-1.2.1.dist-info/WHEEL
pydsxkline-1.2.1.dist-info/top_level.txt
pydsxkline-1.2.1.dist-info/RECORD
