Metadata-Version: 2.1
Name: pydsxkline
Version: 1.2.1
Summary: pydsxkline是一个有趣的python包，一行代码即可显示K线图，主要应用于股票金融量化领域，当您想要把股票数据图形化的时候，可以试试这个小工具，希望能帮到有需要的朋友。
Home-page: https://github.com/dsxkline/dsxkline_python
Author: fangyunsm
Author-email: fangyunsm <934476300@qq.com>
License: MIT License
Project-URL: Homepage, https://github.com/dsxkline/dsxkline_python
Project-URL: Bug Tracker, https://github.com/dsxkline/dsxkline_python/issues
Classifier: Programming Language :: Python :: 3
Classifier: License :: OSI Approved :: MIT License
Classifier: Operating System :: OS Independent
Requires-Python: >=3.6,<4
License-File: LICENSE
Requires-Dist: pywebview
